{
  "type": "FeatureCollection",
  "features": [
    {
      "type": "Feature",
      "properties": {
          "name":"Waterdeep",
          "type":"city"
      },
      "geometry": {
        "type": "Point",
        "coordinates": [-74.81632079967918, 38.63250256772329]
      }
    },
    {
      "type": "Feature",
      "properties": {
          "name":"Neverwinter",
          "type":"city"
      },
      "geometry": {
        "type": "Point",
        "coordinates": [-78.15164102622185, 42.40079024987824]
      }
    },
    {
      "type": "Feature",
      "properties": {
          "name":"Luskan",
          "type":"city"
      },
      "geometry": {
        "type": "Point",
        "coordinates": [-78.79742452523175, 44.450750885576696]
      }
    },
    {
      "type": "Feature",
      "properties": {
          "name":"Baldur's Gate",
          "type":"city"
      },
      "geometry": {
        "type": "Point",
        "coordinates": [-70.60290749930321, 30.545202102349634]
      }
    }
  ]
}